pusher_utils/__init__.py
pusher_utils/utils.py
bear_django_pusher_utils-0.1.0.dist-info/METADATA
bear_django_pusher_utils-0.1.0.dist-info/WHEEL
bear_django_pusher_utils-0.1.0.dist-info/top_level.txt
bear_django_pusher_utils-0.1.0.dist-info/RECORD
