Metadata-Version: 2.4
Name: bear-django-pusher-utils
Version: 0.1.0
Summary: A professional utility function for sending data via Pusher in Django projects.
Author-email: Bohdan Riabunets <bearablyk@gmail.com>
License-Expression: MIT
Project-URL: Homepage, https://github.com/bearablyk/django-pusher-utils
Project-URL: Issues, https://github.com/bearablyk/django-pusher-utils/issues
Keywords: django,pusher,realtime,websocket
Classifier: Development Status :: 5 - Production/Stable
Classifier: Environment :: Web Environment
Classifier: Framework :: Django
Classifier: Framework :: Django :: 4.2
Classifier: Framework :: Django :: 5.0
Classifier: Intended Audience :: Developers
Classifier: Operating System :: OS Independent
Classifier: Programming Language :: Python :: 3
Classifier: Programming Language :: Python :: 3.9
Classifier: Programming Language :: Python :: 3.10
Classifier: Programming Language :: Python :: 3.11
Classifier: Programming Language :: Python :: 3.12
Requires-Python: >=3.8
Requires-Dist: django>=4.2
Requires-Dist: pusher>=3.3
